{
  "id": "keystone",
  "desiredState": {
    "manifest": {
      "version": "v1beta1",
      "id": "keystone-1",
      "containers": [{
        "name": "keystone",
        "image": "larsks/fedora-rdo-keystone",
        "ports": [
          {"containerPort": 5000},
          {"containerPort": 35357}
        ],
        "env": [
          {"name": "DB_ROOT_PASSWORD", "value": "password"},
          {"name": "KEYSTONE_ADMIN_TOKEN", "value": "ADMINTOKEN"}
        ]
      },{
      	"name": "keystone-hautoproxy",
	"image": "larsks/fedora-rdo-hautoproxy"
      }]
    }
  },
  "labels": {
    "name": "keystone"
  }
}
